bulletind/__init__.py
bulletind/__main__.py
bulletind/__version__.py
bulletind/py.typed
bulletind/data/bulletind-021.json
bulletind/data/bulletind-022.json
bulletind/data/bulletind-023.json
bulletind/data/bulletind-024.json
bulletind/data/bulletind-028.json
bulletind/data/bulletind-030.json
bulletind/data/bulletind-031.json
bulletind/data/bulletind-032.json
bulletind/data/bulletind-033.json
bulletind/data/bulletind-036.json
bulletind/data/bulletind-037.json
bulletind/data/bulletind-039.json
bulletind/data/bulletind-040.json
bulletind/data/bulletind-041.json
bulletind/data/bulletind-043.json
bulletind/data/bulletind-044.json
bulletind/data/bulletind-046.json
bulletind/data/bulletind-050.json
bulletind/data/bulletind-051.json
bulletind/data/bulletind-052.json
bulletind/data/bulletind-053.json
bulletind/data/bulletind-054.json
bulletind/data/bulletind-055.json
bulletind/data/bulletind-056.json
bulletind/data/bulletind-057.json
bulletind/data/bulletind-058.json
bulletind/data/bulletind-059.json
bulletind/data/bulletind-060.json
bulletind/data/bulletind-061.json
bulletind/data/bulletind-062.json
bulletind/data/bulletind-063.json
bulletind/data/bulletind-064.json
bulletind/data/bulletind-065.json
bulletind/data/bulletind-066.json
bulletind/data/bulletind-067.json
bulletind/data/bulletind-068.json
bulletind/data/bulletind-069.json
bulletind/data/bulletind-070.json
bulletind/data/bulletind-071.json
bulletind/data/bulletind-072.json
bulletind/data/bulletind-073.json
bulletind/data/bulletind-074.json
bulletind/data/bulletind-075.json
bulletind/data/bulletind-076.json
bulletind/data/bulletind-077.json
bulletind/data/bulletind-078.json
bulletind/data/bulletind-079.json
bulletind/data/bulletind-080.json
bulletind/data/bulletind-081.json
bulletind/data/bulletind-082.json
bulletind/data/bulletind-083.json
bulletind/data/bulletind-084.json
bulletind/data/bulletind-085.json
bulletind/data/bulletind-086.json
bulletind/data/bulletind-087.json
bulletind/data/bulletind-088.json
bulletind-0.0.0a5.dist-info/METADATA
bulletind-0.0.0a5.dist-info/WHEEL
bulletind-0.0.0a5.dist-info/entry_points.txt
bulletind-0.0.0a5.dist-info/top_level.txt
bulletind-0.0.0a5.dist-info/RECORD
