Metadata-Version: 2.1
Name: bulletind
Version: 0.0.0a5
Summary: Access IERS "Bulletin D" data
Home-page: https://github.com/jepler/bulletind
Author: Jeff Epler
Author-email: jepler@gmail.com
Classifier: Programming Language :: Python :: 3
Classifier: Programming Language :: Python :: 3.9
Classifier: Programming Language :: Python :: 3.10
Classifier: Programming Language :: Python :: Implementation :: PyPy
Classifier: Programming Language :: Python :: Implementation :: CPython
Classifier: License :: OSI Approved :: GNU General Public License v3 (GPLv3)
Classifier: Operating System :: OS Independent
Requires-Python: >=3.9
Requires-Dist: beautifulsoup4
Requires-Dist: click
Requires-Dist: dataclasses-json
Requires-Dist: platformdirs
Requires-Dist: requests
Provides-Extra: dev
Requires-Dist: build ; extra == 'dev'
Requires-Dist: mypy ; extra == 'dev'
Requires-Dist: twine ; extra == 'dev'
Requires-Dist: types-requests ; extra == 'dev'
Requires-Dist: types-beautifulsoup4 ; extra == 'dev'
